{"cameraMode":{"drawMode":0,"name":"Shaded","section":"Shading Mode"},"sceneLighting":true,"audioPlay":false,"sceneViewState":{"showFog":true,"showMaterialUpdate":true,"showSkybox":true,"showFlares":true,"showImageEffects":false,"showParticleSystems":true,"showVisualEffectGraphs":true,"m_FxEnabled":true},"in2DMode":false,"pivot":{"x":-6.340397357940674,"y":-13.567294120788575,"z":4.4294114112854},"rotation":{"x":0.570132315158844,"y":-0.15062837302684785,"z":0.10728473216295243,"w":0.8004709482192993},"size":9.985871315002442,"orthographic":false}